rdeep.py
rdeep-0.0.1.dist-info/LICENSE.txt
rdeep-0.0.1.dist-info/METADATA
rdeep-0.0.1.dist-info/WHEEL
rdeep-0.0.1.dist-info/top_level.txt
rdeep-0.0.1.dist-info/RECORD
